git-magic-fixup
setup.py
gitmagic/__init__.py
gitmagic/change.py
gitmagic/commit_range.py
gitmagic/fixup.py
gitmagic/fixupdestinationpicker.py
gitmagic/interactive.py
gitmagic.egg-info/PKG-INFO
gitmagic.egg-info/SOURCES.txt
gitmagic.egg-info/dependency_links.txt
gitmagic.egg-info/requires.txt
gitmagic.egg-info/top_level.txt