Metadata-Version: 1.1
Name: gitmagic
Version: 0.1
Summary: All the magical things that git misses.
Home-page: https://github.com/balabit/git-magic
Author: Peter Hajdu
Author-email: peter.ferenc.hajdu@gmail.com
License: UNKNOWN
Download-URL: https://github.com/balabit/git-magic/tarball/0.1
Keywords: git,magic,fixup
Platform: UNKNOWN
